{
    "lessons": [
        {
            "id": "l1",
            "title": "Welcome to the Blue Team",
            "description": "What is Cybersecurity and why is Defense crucial?",
            "xpReward": 20,
            "estimatedMinutes": 5,
            "section": "Introduction"
        },
        {
            "id": "l2",
            "title": "Anatomy of a SOC",
            "description": "Inside the Security Operations Center: People, Process, Technology.",
            "xpReward": 25,
            "estimatedMinutes": 6,
            "section": "Core Concepts"
        },
        {
            "id": "l3",
            "title": "The Tier 1 Analyst Mindset",
            "description": "What does a day look like? Alert fatigue vs. True Positive.",
            "xpReward": 25,
            "estimatedMinutes": 7,
            "section": "Roles"
        },
        {
            "id": "l4",
            "title": "The Attacker's Playbook",
            "description": "Know your enemy: Cyber Kill Chain and basic hacker motivations.",
            "xpReward": 25,
            "estimatedMinutes": 6,
            "section": "Core Concepts"
        },
        {
            "id": "l5",
            "title": "Your Defensive Arsenal",
            "description": "Overview of the tools we'll master: SIEM, EDR, Firewall, Proxy.",
            "xpReward": 25,
            "estimatedMinutes": 5,
            "section": "Tools"
        }
    ]
}