{
    "id": "l2",
    "chapterId": "ch_2",
    "title": "Where Am I? The `pwd` Command",
    "description": "Never get lost again. Learn the command that tells you exactly where you are in the tree.",
    "xpReward": 20,
    "estimatedMinutes": 5,
    "section": "Navigation Basics",
    "slides": [
        {
            "id": "s_l2_1",
            "type": "text",
            "title": "The You Are Here Arrow đź“Ť",
            "content": "# Print Working Directory\n\nIn a shopping mall, you look for the map with the big red arrow that says **'YOU ARE HERE'**.\n\nIn the Linux terminal, you type:\n\n```bash\npwd\n```\n\n`pwd` stands for **P**rint **W**orking **D**irectory.\n\nIt's the simplest command in the world. It has no options. It has no arguments. It just tells you exactly where you are standing in the filesystem tree."
        },
        {
            "id": "s_l2_2",
            "type": "code",
            "title": "See it in Action",
            "content": "Open your terminal. You will likely be in your Home directory. Type `pwd` and press Enter.",
            "codeSnippet": "pwd",
            "codeLanguage": "bash",
            "canRunCode": true
        },
        {
            "id": "s_l2_3",
            "type": "text",
            "title": "Decoding the Output đź”Ž",
            "content": "# What does `/home/cybron` mean?\n\nWhen you run `pwd`, you might see:\n\n`/home/cybron`\n\nLet's break this down from left to right using our tree analogy.\n\n1.  `/` : **Start at the root of the tree.**\n2.  `home/` : **Go to the 'home' branch.**\n3.  `cybron/` : **Go to the 'cybron' sub-branch.**\n\nThis is called a **Path**. It's the specific address of your location.\n\n> **Note:** The slashes `/` separate the different levels of the tree."
        },
        {
            "id": "s_l2_4",
            "type": "quiz",
            "title": "Quick Check đź§ ",
            "content": "",
            "quizData": {
                "id": "q_l2_1",
                "type": "fill_blank",
                "question": "The command to display your current location in the filesystem is _____.",
                "options": [
                    "ls",
                    "cd",
                    "pwd",
                    "locate"
                ],
                "correctAnswer": "pwd",
                "explanation": "`pwd` stands for Print Working Directory.",
                "xpReward": 10
            }
        },
        {
            "id": "s_l2_5",
            "type": "tip",
            "title": "Pro Tip đźš€",
            "content": "## The Prompt Knows Too\n\nLook at your command prompt:\n\n`user@hostname:~$`\n\nSee that `~`? That's shorthand for your **Home Directory**. If `pwd` says `/home/cybron`, the prompt will show `~`.\n\nWe'll cover `~` in detail later, but just know that the prompt is always giving you a hint about where you are."
        }
    ]
}