{
  "id": "l1",
  "chapterId": "ch_10",
  "title": "Hacking for Good 🎓",
  "description": "Ethics, law, and the rules of engagement.",
  "xpReward": 25,
  "estimatedMinutes": 5,
  "section": "Ethics",
  "slides": [
    {
      "id": "s_l1_1",
      "type": "text",
      "title": "The fine line 🎓",
      "content": "### Ethical Hacking\n\nYou now have the knowledge to do significant damage. But with great power comes the responsibility to stay on the right side of the law.\n\nAn **Ethical Hacker** (White Hat) uses their skills to help organizations find and fix bugs, always with **written permission**."
    },
    {
      "id": "s_l1_2",
      "type": "warning",
      "title": "The Law 🛑",
      "content": "### Computer Misuse Act\n\nIn most countries (like the US and UK), it is illegal to:\n\n1.  Access a computer without permission.\n2.  Access a computer with intent to commit a crime.\n3.  Impair the operation of a computer (DoS).\n\n**Ignorance is not a defense.** Even 'testing' a friend's website without their permission can get you into legal trouble."
    },
    {
      "id": "s_l1_3",
      "type": "quiz",
      "title": "Ethics Quiz 🧠",
      "content": "",
      "quizData": {
        "id": "q_l1_1",
        "type": "multiple_choice",
        "question": "What is the absolute most important requirement before performing a security test on a client's network?",
        "options": [
          {"id": "opt1", "text": "A fast internet connection", "isCorrect": false},
          {"id": "opt2", "text": "Signed, written authorization (The Contract)", "isCorrect": true},
          {"id": "opt3", "text": "The latest version of Kali Linux", "isCorrect": false}
        ],
        "explanation": "Without written permission, you're just a hacker. With it, you're a professional consultant.",
        "xpReward": 10
      }
    }
  ]
}
